sparsity_generator/__init__.py
sparsity_generator/inter_sparsity_packet.py
sparsity_generator-0.1.1.dist-info/METADATA
sparsity_generator-0.1.1.dist-info/WHEEL
sparsity_generator-0.1.1.dist-info/top_level.txt
sparsity_generator-0.1.1.dist-info/RECORD
